PathwayOracle/__init__.py
PathwayOracle/db.py
PathwayOracle/AgentFiles/Agent.py
PathwayOracle/AgentFiles/BertEmbeddings.py
PathwayOracle/AgentFiles/CommonOnto.py
PathwayOracle/AgentFiles/FunctionTool.py
PathwayOracle/AgentFiles/OntoTool.py
PathwayOracle/AgentFiles/PubFindTool.py
PathwayOracle/AgentFiles/TextSearch.py
PathwayOracle/KGInstance/KGAnalysis.py
PathwayOracle/KGInstance/KGCypher.py
PathwayOracle/KGInstance/KGInstance.py
PathwayOracle/KGInstance/KGMark.py
PathwayOracle/KGInstance/KGRetrieval.py
PathwayOracle/KGInstance/PA_KG.py
PathwayOracle/LLM_Summarization/LLM_Sum.py
PathwayOracle/PathwayAnalysis/PA_Analyzer.py
PathwayOracle/PathwayAnalysis/edge_list.txt
PathwayOracle/PathwayAnalysis/netGSA.R
pathwayoracle-2.0.2.dist-info/METADATA
pathwayoracle-2.0.2.dist-info/WHEEL
pathwayoracle-2.0.2.dist-info/licenses/LICENSE
pathwayoracle-2.0.2.dist-info/RECORD
