Metadata-Version: 2.3
Name: PathwayOracle
Version: 2.0.2
Summary: An LLM-empowered, KG-Driven, Gene Pathway Analysis Tool
Project-URL: Homepage, https://github.com/yoyo4581/PathwayOracle
Project-URL: Issues, https://github.com/yoyo4581/PathwayOracle/issues
Author-email: Yahya Al Sabeh <yahyaalsabeh@gmail.com>
Classifier: License :: OSI Approved :: GNU General Public License v3 or later (GPLv3+)
Classifier: Operating System :: OS Independent
Classifier: Programming Language :: Python :: 3
Requires-Python: ==3.10.15
Requires-Dist: hdbscan
Requires-Dist: langchain
Requires-Dist: langchain-community
Requires-Dist: langchain-core
Requires-Dist: langchain-openai
Requires-Dist: langchain-text-splitters
Requires-Dist: langgraph
Requires-Dist: matplotlib
Requires-Dist: neo4j
Requires-Dist: numpy
Requires-Dist: python-dotenv
Requires-Dist: requests
Requires-Dist: scikit-learn
Requires-Dist: torch
Requires-Dist: torchaudio
Requires-Dist: torchvision
Requires-Dist: transformers
